pywershell/.deprecated/__init__.py
pywershell/.deprecated/deprecated_init.py
pywershell/.deprecated/pywershell.ps1
pywershell/.deprecated/pywersl.py
pywershell/.wip/__init__.py
pywershell/.wip/async_type.py
pywershell/__init__.py
pywershell/pkg_wsl/__init__.py
pywershell/pkg_wsl/mod_debian.py
pywershell/pkg_wsl/mod_util.py
pywershell/pkg_wsl/mod_wsl.py
pywershell-0.3.12.dist-info/licenses/LICENSE
pywershell-0.3.12.dist-info/METADATA
pywershell-0.3.12.dist-info/WHEEL
pywershell-0.3.12.dist-info/RECORD
