Metadata-Version: 2.4
Name: pywershell
Version: 0.3.12
Summary: 
License-File: LICENSE
Author: Miles Copeland Luce
Requires-Python: >=3.13
Classifier: Programming Language :: Python :: 3
Classifier: Programming Language :: Python :: 3.13
Classifier: Programming Language :: Python :: 3.14
Requires-Dist: annotated-dict (>=0.1.0,<0.2.0)
